libresubtitles/__init__.py
libresubtitles/cli.py
libresubtitles/core/__init__.py
libresubtitles/core/audio.py
libresubtitles/core/globals.py
libresubtitles/core/splitter.py
libresubtitles/core/srt.py
libresubtitles/core/stt.py
libresubtitles-1.0.3.dist-info/LICENSE
libresubtitles-1.0.3.dist-info/METADATA
libresubtitles-1.0.3.dist-info/WHEEL
libresubtitles-1.0.3.dist-info/entry_points.txt
libresubtitles-1.0.3.dist-info/RECORD
