Metadata-Version: 2.3
Name: libresubtitles
Version: 1.0.3
Summary: Privacy-first AI subtitles for videos and audio
Author: Chirag Juneja
Author-email: chiragjuneja6@gmail.com
Requires-Python: >=3.13
Classifier: Programming Language :: Python :: 3
Classifier: Programming Language :: Python :: 3.13
Requires-Dist: argparse (>=1.4.0,<2.0.0)
Requires-Dist: audioop-lts (>=0.2.2,<0.3.0)
Requires-Dist: ipython (>=9.5.0,<10.0.0)
Requires-Dist: openai-whisper (>=20250625,<20250626)
Requires-Dist: pydub (>=0.25.1,<0.26.0)
